butterflow/__init__.py
butterflow/__main__.py
butterflow/tests/__init__.py
butterflow/tests/test_butterflow.py
butterflow-0.0.1.dist-info/LICENSE
butterflow-0.0.1.dist-info/METADATA
butterflow-0.0.1.dist-info/WHEEL
butterflow-0.0.1.dist-info/entry_points.txt
butterflow-0.0.1.dist-info/top_level.txt
butterflow-0.0.1.dist-info/RECORD
