Metadata-Version: 2.1
Name: butterflow
Version: 0.0.1
Summary: Python project
Home-page: https://john.doe.org
Author: Kristian Boda
Author-email: kristian.boda@babylonhealth.com
License: MIT
Platform: UNKNOWN
Classifier: Programming Language :: Python :: 3
